Metadata-Version: 1.0
Name: Gen-Gaus-Bi-distributions
Version: 0.1
Summary: Gaussian distributions
Home-page: UNKNOWN
Author: Satoe Yokoyama
Author-email: UNKNOWN
License: UNKNOWN
Platform: UNKNOWN
